cvc/__init__.py
cvc/_version.py
cvc/asn1.py
cvc/certificates.py
cvc/ec_curves.py
cvc/oid.py
cvc/terminal.py
cvc/utils.py
cvc/tools/__init__.py
cvc/tools/cvc_create.py
cvc/tools/cvc_print.py
pycvc-1.5.0.dist-info/METADATA
pycvc-1.5.0.dist-info/WHEEL
pycvc-1.5.0.dist-info/entry_points.txt
pycvc-1.5.0.dist-info/top_level.txt
pycvc-1.5.0.dist-info/RECORD
